adl/__init__.py
adl/adl.py
adl/antidot.py
adl/lattice.py
adl/parms.py
adl-0.1.5.dist-info/LICENSE
adl-0.1.5.dist-info/METADATA
adl-0.1.5.dist-info/WHEEL
adl-0.1.5.dist-info/top_level.txt
adl-0.1.5.dist-info/RECORD
