Metadata-Version: 2.1
Name: adl
Version: 0.1.5
Summary: script generator for mumax3 for antidot lattice
Home-page: https://github.com/MathieuMoalic/adl
Author: Mathieu Moalic
Author-email: matmoa@pm.me
License: GPL-3.0
Platform: any
